pygor/__init__.py
pygor/binarywave.py
pygor/core.py
pygor/packed.py
pygor/struct.py
pygor/util.py
pygor/record/__init__.py
pygor/record/base.py
pygor/record/folder.py
pygor/record/history.py
pygor/record/packedfile.py
pygor/record/procedure.py
pygor/record/variables.py
pygor/record/wave.py
pygor-1.0.1.dist-info/METADATA
pygor-1.0.1.dist-info/WHEEL
pygor-1.0.1.dist-info/licenses/COPYING
pygor-1.0.1.dist-info/RECORD
