Metadata-Version: 2.4
Name: pygor
Version: 1.0.1
Summary: Package for loading binary IGOR binary
Author-email: "W. Trevor King" <wking@tremily.us>, Jacob Gobbo <gobbo.jacob@gmail.com>
License-File: COPYING
Requires-Python: >=3.12
Requires-Dist: numpy>=2.0.0
